metamart_source_dbt/__init__.py
metamart_source_dbt/adapters/__init__.py
metamart_source_dbt/adapters/adapters.py
metamart_source_dbt/adapters/v5.py
metamart_source_dbt/base.py
metamart_source_dbt/data/graph.gpickle
metamart_source_dbt/data/manifest.json
metamart_source_dbt/data_tools.py
metamart_source_dbt/loaders/__init__.py
metamart_source_dbt/loaders/base.py
metamart_source_dbt/loaders/utils.py
metamart_source_dbt/loaders/v1.py
metamart_source_dbt/loaders/v10.py
metamart_source_dbt/loaders/v11.py
metamart_source_dbt/loaders/v2.py
metamart_source_dbt/loaders/v3.py
metamart_source_dbt/loaders/v4.py
metamart_source_dbt/loaders/v5.py
metamart_source_dbt/loaders/v6.py
metamart_source_dbt/loaders/v7.py
metamart_source_dbt/loaders/v8.py
metamart_source_dbt/loaders/v9.py
metamart_source_dbt/models/__init__.py
metamart_source_dbt/models/metamart.py
metamart_source_dbt/models/shared.py
metamart_source_dbt/package_definitions.py
metamart_source_dbt/processor.py
metamart_source_dbt/py.typed
metamart_source_dbt/utils.py
metamart_source_dbt-0.3.5.dist-info/METADATA
metamart_source_dbt-0.3.5.dist-info/WHEEL
metamart_source_dbt-0.3.5.dist-info/RECORD
